tacitus/__init__.py
tacitus/adapters/__init__.py
tacitus/adapters/sqlalchemy/__init__.py
tacitus/adapters/sqlalchemy/building.py
tacitus/adapters/sqlalchemy/connecting.py
tacitus/adapters/sqlalchemy/generic.py
tacitus/adapters/sqlalchemy/obtaining.py
tacitus/adapters/sqlalchemy/registration.py
tacitus/adapters/sqlalchemy/saving.py
tacitus/adapters/sqlalchemy/vendoring.py
tacitus/definitions/__init__.py
tacitus/definitions/contracts.py
tacitus/definitions/exceptions.py
tacitus-1.0.2.dist-info/WHEEL
tacitus-1.0.2.dist-info/METADATA
tacitus-1.0.2.dist-info/RECORD
