Metadata-Version: 2.1
Name: tacitus
Version: 1.0.2
Summary: 
Author: Smairon
Author-email: man@smairon.ru
Requires-Python: >=3.10,<4.0
Classifier: Programming Language :: Python :: 3
Classifier: Programming Language :: Python :: 3.10
Classifier: Programming Language :: Python :: 3.11
Requires-Dist: orjson (>=3.8.3,<4.0.0)
Requires-Dist: python-dateutil (>=2.8.2,<3.0.0)
Requires-Dist: sqlalchemy (>=1.4.39,<2.0.0)
